<annotation>
	<folder>ship</folder>
	<filename>哈尔西·鲍威尔.png</filename>
	<path>D:\document\idea\blhx-wiki-mirai-plugin\data\blhx-wiki\image\ship\哈尔西·鲍威尔.png</path>
	<source>
		<database>Unknown</database>
	</source>
	<size>
		<width>1402</width>
		<height>1254</height>
		<depth>3</depth>
	</size>
	<segmented>0</segmented>
	<object>
		<name>person</name>
		<pose>Unspecified</pose>
		<truncated>0</truncated>
		<difficult>0</difficult>
		<bndbox>
			<xmin>243</xmin>
			<ymin>74</ymin>
			<xmax>891</xmax>
			<ymax>932</ymax>
		</bndbox>
	</object>
</annotation>
