<annotation>
	<folder>ship</folder>
	<filename>莫妮卡.png</filename>
	<path>D:\document\idea\blhx-wiki-mirai-plugin\data\blhx-wiki\image\ship\莫妮卡.png</path>
	<source>
		<database>Unknown</database>
	</source>
	<size>
		<width>2048</width>
		<height>1926</height>
		<depth>3</depth>
	</size>
	<segmented>0</segmented>
	<object>
		<name>person</name>
		<pose>Unspecified</pose>
		<truncated>0</truncated>
		<difficult>0</difficult>
		<bndbox>
			<xmin>773</xmin>
			<ymin>295</ymin>
			<xmax>1307</xmax>
			<ymax>1019</ymax>
		</bndbox>
	</object>
</annotation>
