<annotation>
	<folder>ship</folder>
	<filename>马布尔黑德.png</filename>
	<path>D:\document\idea\blhx-wiki-mirai-plugin\data\blhx-wiki\image\ship\马布尔黑德.png</path>
	<source>
		<database>Unknown</database>
	</source>
	<size>
		<width>1400</width>
		<height>1383</height>
		<depth>3</depth>
	</size>
	<segmented>0</segmented>
	<object>
		<name>person</name>
		<pose>Unspecified</pose>
		<truncated>0</truncated>
		<difficult>0</difficult>
		<bndbox>
			<xmin>309</xmin>
			<ymin>15</ymin>
			<xmax>968</xmax>
			<ymax>941</ymax>
		</bndbox>
	</object>
</annotation>
